MANIFEST.in
setup.cfg
setup.py
facsimile/VERSION
facsimile/requirements-test.txt
facsimile/requirements.txt
vodka_xbahn/__init__.py
vodka_xbahn/plugin.py
vodka_xbahn.egg-info/PKG-INFO
vodka_xbahn.egg-info/SOURCES.txt
vodka_xbahn.egg-info/dependency_links.txt
vodka_xbahn.egg-info/entry_points.txt
vodka_xbahn.egg-info/requires.txt
vodka_xbahn.egg-info/top_level.txt
vodka_xbahn.egg-info/zip-safe