Metadata-Version: 1.1
Name: vodka-xbahn
Version: 0.9.1
Summary: xbahn plugin for vodka
Home-page: https://github.com/20c/vodka-xbahn
Author: 20C
Author-email: code@20c.com
License: LICENSE.txt
Download-URL: https://github.com/20c/vodka-xbahn/0.9.1
Platform: UNKNOWN
Classifier: Development Status :: 4 - Beta
Classifier: Programming Language :: Python :: 2.7
Classifier: Programming Language :: Python :: 3.4
Classifier: License :: OSI Approved :: Apache Software License
